Blok Pink (Encoder)/fixed_point_add.v
module fixed_point_add
(
    input [31:0] A,  // Fixed-point input A
    input [31:0] B,  // Fixed-point input B
    output [31:0] C  // Hasil output
);
    // Ekstraksi bagian sign dan value dari kedua input
    wire sign_A = A[31];           // Sign bit A
    wire sign_B = B[31];           // Sign bit B
    wire [30:0] value_A = A[30:0]; // Value A (mantissa + exponent dalam satu nilai)
    wire [30:0] value_B = B[30:0]; // Value B (mantissa + exponent dalam satu nilai)

    // Tentukan hasil sign dan nilai akhir
    wire result_sign;
    wire new_result_sign;
    wire [30:0] result_value;

    // Jika sign bit sama, lakukan penjumlahan, jika berbeda, lakukan pengurangan
    assign result_sign = (sign_A == sign_B) ? sign_A : (value_A > value_B ? sign_A : sign_B);

    // Jika sign bit sama, tambahkan value, jika berbeda, kurangi value
    assign result_value = (sign_A == sign_B) ? (value_A + value_B) : 
                          (value_A > value_B ? (value_A - value_B) : (value_B - value_A));

    assign new_result_sign = (result_value == 0) ? 0 : result_sign;

    // Tentukan hasil akhir, gabungkan sign dan value
    assign C = {new_result_sign, result_value};

endmodule

RTL/Kode Sigmoid 8 Slice/fixed_point_multiply.v
module fixed_point_multiply (
    input  [31:0] A,  // 32-bit fixed-point input (sign-magnitude)
    input  [31:0] B,  // 32-bit fixed-point input (sign-magnitude)
    output [31:0] C   // 32-bit fixed-point output (sign-magnitude)
);
    // Extract sign bits
    wire sign_A = A[31];
    wire sign_B = B[31];

    // Extract magnitude (mantissa + fraction)
    wire [30:0] mag_A = A[30:0];
    wire [30:0] mag_B = B[30:0];

    // Multiply magnitudes (unsigned multiplication)
    wire [61:0] product_unsigned = mag_A * mag_B;

    // Normalize the result by right-shifting 27 bits
    wire [31:0] normalized_product = product_unsigned[58:27]; // Keep 31 bits (including 1 for sign)

    // Determine the sign of the result
    wire result_sign = sign_A ^ sign_B; // XOR for determining sign

    // Combine sign and magnitude into final output
    assign C = {result_sign, normalized_product[30:0]}; // Concatenate sign and magnitude
endmodule

RTL/Kode Softplus 8 Slice/compare_8float.v
module compare_8float (
    input wire [31:0] data, x1, x2, x3, x4, x5, x6, x7, x8, // Sign-magnitude inputs
    input wire [31:0] m1, m2, m3, m4, m5, m6, m7, m8, m9,
    input wire [31:0] c1, c2, c3, c4, c5, c6, c7, c8, c9,
    output reg [31:0] m, c
);

    wire [7:0] flag;

    // Split the inputs into sign and magnitude
    wire data_sign = data[31];
    wire [30:0] data_mag = data[30:0];
    
    wire x1_sign = x1[31];
    wire [30:0] x1_mag = x1[30:0];

    wire x2_sign = x2[31];
    wire [30:0] x2_mag = x2[30:0];

    wire x3_sign = x3[31];
    wire [30:0] x3_mag = x3[30:0];

    wire x4_sign = x4[31];
    wire [30:0] x4_mag = x4[30:0];

    wire x5_sign = x5[31];
    wire [30:0] x5_mag = x5[30:0];

    wire x6_sign = x6[31];
    wire [30:0] x6_mag = x6[30:0];

    wire x7_sign = x7[31];
    wire [30:0] x7_mag = x7[30:0];

    wire x8_sign = x8[31];
    wire [30:0] x8_mag = x8[30:0];

    // Helper function to compare sign-magnitude numbers
    function compare_sign_mag;
        input sign_a, sign_b;
        input [30:0] mag_a, mag_b;
        begin
            if (sign_a != sign_b) begin
                // If signs differ, the negative number is smaller
                compare_sign_mag = (sign_a > sign_b);  // 1 if A < B
            end else begin
                // If signs are the same, compare magnitudes
                if (sign_a == 1'b1) begin
                    // Both negative: larger magnitude means smaller number
                    compare_sign_mag = (mag_a > mag_b);
                end else begin
                    // Both positive: larger magnitude means larger number
                    compare_sign_mag = (mag_a < mag_b);
                end
            end
        end
    endfunction

    // Generate flags for region checks
    assign flag[0] = compare_sign_mag(data_sign, x1_sign, data_mag, x1_mag); // Region 1
    assign flag[1] = compare_sign_mag(data_sign, x2_sign, data_mag, x2_mag); // Region 2
    assign flag[2] = compare_sign_mag(data_sign, x3_sign, data_mag, x3_mag); // Region 3
    assign flag[3] = compare_sign_mag(data_sign, x4_sign, data_mag, x4_mag); // Region 4
    assign flag[4] = compare_sign_mag(data_sign, x5_sign, data_mag, x5_mag); // Region 5
    assign flag[5] = compare_sign_mag(data_sign, x6_sign, data_mag, x6_mag); // Region 6
    assign flag[6] = compare_sign_mag(data_sign, x7_sign, data_mag, x7_mag); // Region 7
    assign flag[7] = compare_sign_mag(data_sign, x8_sign, data_mag, x8_mag); // Region 8

    // Determine m and c based on flag
    always @(*) begin
        if (flag[0]) begin
            m = m1;
            c = c1;
        end else if (flag[1]) begin
            m = m2;
            c = c2;
        end else if (flag[2]) begin
            m = m3;
            c = c3;
        end else if (flag[3]) begin
            m = m4;
            c = c4;
        end else if (flag[4]) begin
            m = m5;
            c = c5;
        end else if (flag[5]) begin
            m = m6;
            c = c6;
        end else if (flag[6]) begin
            m = m7;
            c = c7;
        end else if (flag[7]) begin
            m = m8;
            c = c8;
        end else begin
            m = m9;
            c = c9;
        end
    end

endmodule

RTL/Kode Softplus 8 Slice/softplus_8slice.v
`include "compare_8float.v"
`include "fixed_point_multiply.v"
`include "fixed_point_add.v"

module softplus_8slice (
    input wire  [31:0] data_in,
    output wire [31:0] data_out
);

    // Inisialisasi nilai m dan c untuk setiap slice
    reg [31:0] m1 = 32'b00000000000010100000100000110110; // value m1 untuk garis 1
    reg [31:0] c1 = 32'b00000000010100001111000110001001; // value c1 untuk garis 1

    reg [31:0] m2 = 32'b00000000011000110011110000111110; // value m2 untuk garis 2
    reg [31:0] c2 = 32'b00000001101010101001101110010111; // value c2 untuk garis 2

    reg [31:0] m3 = 32'b00000001001110001111111111001101; // value m3 untuk garis 3
    reg [31:0] c3 = 32'b00000011100011111101111101110000; // value c3 untuk garis 3

    reg [31:0] m4 = 32'b00000010011111100010010110011111; // value m4 untuk garis 4
    reg [31:0] c4 = 32'b00000101000111000001011011001010; // value c4 untuk garis 4

    reg [31:0] m5 = 32'b00000011111111110011000110011101; // value m5 untuk garis 5
    reg [31:0] c5 = 32'b00000101101100011001111010110010; // value c5 untuk garis 5

    reg [31:0] m6 = 32'b00000101100000011010110011001100; // value m6 untuk garis 6
    reg [31:0] c6 = 32'b00000101000111001100001110100101; // value c6 untuk garis 6

    reg [31:0] m7 = 32'b00000011100011100010001000001111; // value m7 untuk garis 7
    reg [31:0] c7 = 32'b00001010101001110110011101001110; // value c7 untuk garis 7

    reg [31:0] m8 = 32'b00000001101010011000101100001000; // value m8 untuk garis 8
    reg [31:0] c8 = 32'b00001100011110110011100010101010; // value c8 untuk garis 8

    reg [31:0] m9 = 32'b00000111111101011111000011110100; // value m9 untuk garis 9
    reg [31:0] c9 = 32'b00000000010100010010100000110111; // value c9 untuk garis 9

    // Nilai batas x
    reg [31:0] x1 = 32'b10011111000000000000100111010010;
    reg [31:0] x2 = 32'b10010010001010010010100100100010;
    reg [31:0] x3 = 32'b10001001101111111010001100110000;
    reg [31:0] x4 = 32'b10000011000110110101010001101110;
    reg [31:0] x5 = 32'b00000011000101001100110011010100;
    reg [31:0] x6 = 32'b00001001110001010001110001000111;
    reg [31:0] x7 = 32'b00010010001101011000110000111100;
    reg [31:0] x8 = 32'b00011110111110001110100110010110;

    wire [31:0] m_out;
    wire [31:0] c_out;

    // Instansiasi modul compare_8float untuk menentukan m dan c berdasarkan slice
    compare_8float custom_mux (
        .data  (data_in),
        .x1    (x1),
        .x2    (x2),
        .x3    (x3),
        .x4    (x4),
        .x5    (x5),
        .x6    (x6),
        .x7    (x7),
        .x8    (x8),
        .m1    (m1),
        .m2    (m2),
        .m3    (m3),
        .m4    (m4),
        .m5    (m5),
        .m6    (m6),
        .m7    (m7),
        .m8    (m8),
        .m9    (m9),
        .c1    (c1),
        .c2    (c2),
        .c3    (c3),
        .c4    (c4),
        .c5    (c5),
        .c6    (c6),
        .c7    (c7),
        .c8    (c8),
        .c9    (c9),
        .m     (m_out),
        .c     (c_out)
    );

    // Implementasi y = m*x + c sebagai piecewise linear approximation (PLA)
    // Perkalian
    wire [31:0] out_mul;
    fixed_point_multiply custom_mul (
        .A (data_in),
        .B (m_out),
        .C (out_mul)
    );

    // Penjumlahan
    fixed_point_add custom_add (
        .A (out_mul),
        .B (c_out),
        .C (data_out)
    );

endmodule

RTL/Kode Softplus 8 Slice/softplus_8slice_tb.v
`include "softplus_8slice.v"

module softplus_8slice_tb;
    // Input
    reg signed [31:0] in;

    // Output
    wire signed [31:0] out;

    softplus_8slice test (
        .data_in (in),
        .data_out(out)
    );

initial begin
    $dumpfile("softplus_8slice_tb.vcd");
    $dumpvars(0, softplus_8slice_tb);

    // Test inuts
    in = 32'b10100000000000000000000000000000;   // -4
    #10;
    in = 32'b10011000000000000000000000000000;   // -3
    #10;
    in = 32'b10010000000000000000000000000000;   // -2
    #10;
    in = 32'b10001000000000000000000000000000;   // -1
    #10;
    in = 32'b00000000000000000000000000000000;   // 0
    #10;
    in = 32'b00001000000000000000000000000000;   // 1
    #10;
    in = 32'b00010000000000000000000000000000;   // 2
    #10;
    in = 32'b00011000000000000000000000000000;   // 3
    #10;
    in = 32'b00100000000000000000000000000000;   // 4
    #10;
    
    $finish;
end

endmodule

RTL/Kode Softplus 8 Slice/softplus_8slice_tb.vcd
$date
	Sat Nov 23 19:20:24 2024
$end
$version
	Icarus Verilog
$end
$timescale
	1s
$end
$scope module softplus_8slice_tb $end
$var wire 32 ! out [31:0] $end
$var reg 32 " in [31:0] $end
$scope module test $end
$var wire 32 # data_in [31:0] $end
$var wire 32 $ out_mul [31:0] $end
$var wire 32 % m_out [31:0] $end
$var wire 32 & data_out [31:0] $end
$var wire 32 ' c_out [31:0] $end
$var reg 32 ( c1 [31:0] $end
$var reg 32 ) c2 [31:0] $end
$var reg 32 * c3 [31:0] $end
$var reg 32 + c4 [31:0] $end
$var reg 32 , c5 [31:0] $end
$var reg 32 - c6 [31:0] $end
$var reg 32 . c7 [31:0] $end
$var reg 32 / c8 [31:0] $end
$var reg 32 0 c9 [31:0] $end
$var reg 32 1 m1 [31:0] $end
$var reg 32 2 m2 [31:0] $end
$var reg 32 3 m3 [31:0] $end
$var reg 32 4 m4 [31:0] $end
$var reg 32 5 m5 [31:0] $end
$var reg 32 6 m6 [31:0] $end
$var reg 32 7 m7 [31:0] $end
$var reg 32 8 m8 [31:0] $end
$var reg 32 9 m9 [31:0] $end
$var reg 32 : x1 [31:0] $end
$var reg 32 ; x2 [31:0] $end
$var reg 32 < x3 [31:0] $end
$var reg 32 = x4 [31:0] $end
$var reg 32 > x5 [31:0] $end
$var reg 32 ? x6 [31:0] $end
$var reg 32 @ x7 [31:0] $end
$var reg 32 A x8 [31:0] $end
$scope module custom_add $end
$var wire 31 B value_B [30:0] $end
$var wire 31 C value_A [30:0] $end
$var wire 1 D sign_B $end
$var wire 1 E sign_A $end
$var wire 31 F result_value [30:0] $end
$var wire 1 G result_sign $end
$var wire 1 H new_result_sign $end
$var wire 32 I C [31:0] $end
$var wire 32 J B [31:0] $end
$var wire 32 K A [31:0] $end
$upscope $end
$scope module custom_mul $end
$var wire 32 L A [31:0] $end
$var wire 1 M result_sign $end
$var wire 1 N sign_B $end
$var wire 1 O sign_A $end
$var wire 62 P product_unsigned [61:0] $end
$var wire 32 Q normalized_product [31:0] $end
$var wire 31 R mag_B [30:0] $end
$var wire 31 S mag_A [30:0] $end
$var wire 32 T C [31:0] $end
$var wire 32 U B [31:0] $end
$upscope $end
$scope module custom_mux $end
$var wire 32 V c1 [31:0] $end
$var wire 32 W c2 [31:0] $end
$var wire 32 X c3 [31:0] $end
$var wire 32 Y c4 [31:0] $end
$var wire 32 Z c5 [31:0] $end
$var wire 32 [ c6 [31:0] $end
$var wire 32 \ c7 [31:0] $end
$var wire 32 ] c8 [31:0] $end
$var wire 32 ^ c9 [31:0] $end
$var wire 32 _ data [31:0] $end
$var wire 32 ` m1 [31:0] $end
$var wire 32 a m2 [31:0] $end
$var wire 32 b m3 [31:0] $end
$var wire 32 c m4 [31:0] $end
$var wire 32 d m5 [31:0] $end
$var wire 32 e m6 [31:0] $end
$var wire 32 f m7 [31:0] $end
$var wire 32 g m8 [31:0] $end
$var wire 32 h m9 [31:0] $end
$var wire 32 i x1 [31:0] $end
$var wire 32 j x2 [31:0] $end
$var wire 32 k x3 [31:0] $end
$var wire 32 l x4 [31:0] $end
$var wire 32 m x5 [31:0] $end
$var wire 32 n x6 [31:0] $end
$var wire 32 o x7 [31:0] $end
$var wire 32 p x8 [31:0] $end
$var wire 1 q x8_sign $end
$var wire 31 r x8_mag [30:0] $end
$var wire 1 s x7_sign $end
$var wire 31 t x7_mag [30:0] $end
$var wire 1 u x6_sign $end
$var wire 31 v x6_mag [30:0] $end
$var wire 1 w x5_sign $end
$var wire 31 x x5_mag [30:0] $end
$var wire 1 y x4_sign $end
$var wire 31 z x4_mag [30:0] $end
$var wire 1 { x3_sign $end
$var wire 31 | x3_mag [30:0] $end
$var wire 1 } x2_sign $end
$var wire 31 ~ x2_mag [30:0] $end
$var wire 1 !" x1_sign $end
$var wire 31 "" x1_mag [30:0] $end
$var wire 8 #" flag [7:0] $end
$var wire 1 $" data_sign $end
$var wire 31 %" data_mag [30:0] $end
$var reg 32 &" c [31:0] $end
$var reg 32 '" m [31:0] $end
$scope function compare_sign_mag $end
$var reg 31 (" mag_a [30:0] $end
$var reg 31 )" mag_b [30:0] $end
$var reg 1 *" sign_a $end
$var reg 1 +" sign_b $end
$upscope $end
$upscope $end
$upscope $end
$upscope $end
$enddefinitions $end
$comment Show the parameter values. $end
$dumpall
$end
#0
$dumpvars
0+"
1*"
b11110111110001110100110010110 )"
b100000000000000000000000000000 ("
b10100000100000110110 '"
b10100001111000110001001 &"
b100000000000000000000000000000 %"
1$"
b11111111 #"
b11111000000000000100111010010 ""
1!"
b10010001010010010100100100010 ~
1}
b1001101111111010001100110000 |
1{
b11000110110101010001101110 z
1y
b11000101001100110011010100 x
0w
b1001110001010001110001000111 v
0u
b10010001101011000110000111100 t
0s
b11110111110001110100110010110 r
0q
b11110111110001110100110010110 p
b10010001101011000110000111100 o
b1001110001010001110001000111 n
b11000101001100110011010100 m
b10000011000110110101010001101110 l
b10001001101111111010001100110000 k
b10010010001010010010100100100010 j
b10011111000000000000100111010010 i
b111111101011111000011110100 h
b1101010011000101100001000 g
b11100011100010001000001111 f
b101100000011010110011001100 e
b11111111110011000110011101 d
b10011111100010010110011111 c
b1001110001111111111001101 b
b11000110011110000111110 a
b10100000100000110110 `
b10100000000000000000000000000000 _
b10100010010100000110111 ^
b1100011110110011100010101010 ]
b1010101001110110011101001110 \
b101000111001100001110100101 [
b101101100011001111010110010 Z
b101000111000001011011001010 Y
b11100011111101111101110000 X
b1101010101001101110010111 W
b10100001111000110001001 V
b10100000100000110110 U
b10000000001010000010000011011000 T
b100000000000000000000000000000 S
b10100000100000110110 R
b1010000010000011011000 Q
b1010000010000011011000000000000000000000000000000 P
1O
0N
1M
b10100000000000000000000000000000 L
b10000000001010000010000011011000 K
b10100001111000110001001 J
b1010001101000010110001 I
0H
0G
b1010001101000010110001 F
1E
0D
b1010000010000011011000 C
b10100001111000110001001 B
b11110111110001110100110010110 A
b10010001101011000110000111100 @
b1001110001010001110001000111 ?
b11000101001100110011010100 >
b10000011000110110101010001101110 =
b10001001101111111010001100110000 <
b10010010001010010010100100100010 ;
b10011111000000000000100111010010 :
b111111101011111000011110100 9
b1101010011000101100001000 8
b11100011100010001000001111 7
b101100000011010110011001100 6
b11111111110011000110011101 5
b10011111100010010110011111 4
b1001110001111111111001101 3
b11000110011110000111110 2
b10100000100000110110 1
b10100010010100000110111 0
b1100011110110011100010101010 /
b1010101001110110011101001110 .
b101000111001100001110100101 -
b101101100011001111010110010 ,
b101000111000001011011001010 +
b11100011111101111101110000 *
b1101010101001101110010111 )
b10100001111000110001001 (
b10100001111000110001001 '
b1010001101000010110001 &
b10100000100000110110 %
b10000000001010000010000011011000 $
b10100000000000000000000000000000 #
b10100000000000000000000000000000 "
b1010001101000010110001 !
$end
#10
b100000001110011011011101 !
b100000001110011011011101 &
b100000001110011011011101 I
b100000001110011011011101 F
b1001010011011010010111010 C
b1101010101001101110010111 B
b11000110011110000111110 R
b10000001001010011011010010111010 $
b10000001001010011011010010111010 K
b10000001001010011011010010111010 T
b1101010101001101110010111 '
b1101010101001101110010111 J
b1101010101001101110010111 &"
b11000110011110000111110 %
b11000110011110000111110 U
b11000110011110000111110 '"
b1001010011011010010111010 Q
b11111110 #"
1+"
b11111000000000000100111010010 )"
b11000000000000000000000000000 ("
b1001010011011010010111010000000000000000000000000000 P
b11000000000000000000000000000 S
b11000000000000000000000000000 %"
b10011000000000000000000000000000 "
b10011000000000000000000000000000 #
b10011000000000000000000000000000 L
b10011000000000000000000000000000 _
#20
b1000111011101111111010110 !
b1000111011101111111010110 &
b1000111011101111111010110 I
b1000111011101111111010110 F
b10011100011111111110011010 C
b11100011111101111101110000 B
b1001110001111111111001101 R
b10000010011100011111111110011010 $
b10000010011100011111111110011010 K
b10000010011100011111111110011010 T
b11100011111101111101110000 '
b11100011111101111101110000 J
b11100011111101111101110000 &"
b1001110001111111111001101 %
b1001110001111111111001101 U
b1001110001111111111001101 '"
b10011100011111111110011010 Q
b11111100 #"
b11111000000000000100111010010 )"
b10000000000000000000000000000 ("
1+"
b10011100011111111110011010000000000000000000000000000 P
b10000000000000000000000000000 S
b10000000000000000000000000000 %"
b10010000000000000000000000000000 "
b10010000000000000000000000000000 #
b10010000000000000000000000000000 L
b10010000000000000000000000000000 _
#30
b10100111011111000100101011 !
b10100111011111000100101011 &
b10100111011111000100101011 I
b10100111011111000100101011 F
b10011111100010010110011111 C
b101000111000001011011001010 B
b10011111100010010110011111 R
b10000010011111100010010110011111 $
b10000010011111100010010110011111 K
b10000010011111100010010110011111 T
b101000111000001011011001010 '
b101000111000001011011001010 J
b101000111000001011011001010 &"
b10011111100010010110011111 %
b10011111100010010110011111 U
b10011111100010010110011111 '"
b10011111100010010110011111 Q
b11111000 #"
b11111000000000000100111010010 )"
b1000000000000000000000000000 ("
1+"
b10011111100010010110011111000000000000000000000000000 P
b1000000000000000000000000000 S
b1000000000000000000000000000 %"
b10001000000000000000000000000000 "
b10001000000000000000000000000000 #
b10001000000000000000000000000000 L
b10001000000000000000000000000000 _
#40
b101101100011001111010110010 !
b101101100011001111010110010 &
b101101100011001111010110010 I
b101101100011001111010110010 F
b0 C
b101101100011001111010110010 B
b11111111110011000110011101 R
0E
b101101100011001111010110010 '
b101101100011001111010110010 J
b101101100011001111010110010 &"
b11111111110011000110011101 %
b11111111110011000110011101 U
b11111111110011000110011101 '"
b0 $
b0 K
b0 T
0M
b0 Q
b11110000 #"
b11111000000000000100111010010 )"
b0 ("
1+"
0*"
0O
b0 P
b0 S
0$"
b0 %"
b0 "
b0 #
b0 L
b0 _
#50
b1010100111100111000001110001 !
b1010100111100111000001110001 &
b1010100111100111000001110001 I
b1010100111100111000001110001 F
b101100000011010110011001100 C
b101000111001100001110100101 B
b101100000011010110011001100 R
b101100000011010110011001100 $
b101100000011010110011001100 K
b101100000011010110011001100 T
b101000111001100001110100101 '
b101000111001100001110100101 J
b101000111001100001110100101 &"
b101100000011010110011001100 %
b101100000011010110011001100 U
b101100000011010110011001100 '"
b101100000011010110011001100 Q
b11100000 #"
b11111000000000000100111010010 )"
b1000000000000000000000000000 ("
1+"
b101100000011010110011001100000000000000000000000000000 P
b1000000000000000000000000000 S
b1000000000000000000000000000 %"
b1000000000000000000000000000 "
b1000000000000000000000000000 #
b1000000000000000000000000000 L
b1000000000000000000000000000 _
#60
b10001110000111010101101101100 !
b10001110000111010101101101100 &
b10001110000111010101101101100 I
b10001110000111010101101101100 F
b111000111000100010000011110 C
b1010101001110110011101001110 B
b11100011100010001000001111 R
b111000111000100010000011110 $
b111000111000100010000011110 K
b111000111000100010000011110 T
b1010101001110110011101001110 '
b1010101001110110011101001110 J
b1010101001110110011101001110 &"
b11100011100010001000001111 %
b11100011100010001000001111 U
b11100011100010001000001111 '"
b111000111000100010000011110 Q
b11000000 #"
b11111000000000000100111010010 )"
b10000000000000000000000000000 ("
1+"
b111000111000100010000011110000000000000000000000000000 P
b10000000000000000000000000000 S
b10000000000000000000000000000 %"
b10000000000000000000000000000 "
b10000000000000000000000000000 #
b10000000000000000000000000000 L
b10000000000000000000000000000 _
#70
b10001011101111101100111000010 !
b10001011101111101100111000010 &
b10001011101111101100111000010 I
b10001011101111101100111000010 F
b100111111001010000100011000 C
b1100011110110011100010101010 B
b1101010011000101100001000 R
b100111111001010000100011000 $
b100111111001010000100011000 K
b100111111001010000100011000 T
b1100011110110011100010101010 '
b1100011110110011100010101010 J
b1100011110110011100010101010 &"
b1101010011000101100001000 %
b1101010011000101100001000 U
b1101010011000101100001000 '"
b100111111001010000100011000 Q
b10000000 #"
b11111000000000000100111010010 )"
b11000000000000000000000000000 ("
1+"
b100111111001010000100011000000000000000000000000000000 P
b11000000000000000000000000000 S
b11000000000000000000000000000 %"
b11000000000000000000000000000 "
b11000000000000000000000000000 #
b11000000000000000000000000000 L
b11000000000000000000000000000 _
#80
b100000001010001110110000000111 !
b100000001010001110110000000111 &
b100000001010001110110000000111 I
b100000001010001110110000000111 F
b11111110101111100001111010000 C
b10100010010100000110111 B
b111111101011111000011110100 R
b11111110101111100001111010000 $
b11111110101111100001111010000 K
b11111110101111100001111010000 T
b10100010010100000110111 '
b10100010010100000110111 J
b10100010010100000110111 &"
b111111101011111000011110100 %
b111111101011111000011110100 U
b111111101011111000011110100 '"
b11111110101111100001111010000 Q
b0 #"
b11111000000000000100111010010 )"
b100000000000000000000000000000 ("
1+"
b11111110101111100001111010000000000000000000000000000000 P
b100000000000000000000000000000 S
b100000000000000000000000000000 %"
b100000000000000000000000000000 "
b100000000000000000000000000000 #
b100000000000000000000000000000 L
b100000000000000000000000000000 _
